aiotcloud/__init__.py
aiotcloud/pyaiot.py
aiotcloud/pyword.py
aiotcloud/aicam/__init__.py
aiotcloud/aicam/tools.py
aiotcloud/aicam/aitool/__init__.py
aiotcloud/aicam/aitool/ai_aruco.py
aiotcloud/aicam/aitool/cam_calib.py
aiotcloud/aicam/aitool/detect_circle.py
aiotcloud/aicam/aitool/detect_color.py
aiotcloud/aicam/aitool/detect_face.py
aiotcloud/aicam/aitool/detect_line.py
aiotcloud/aicam/aitool/detect_marker.py
aiotcloud/aicam/aitool/detect_trace.py
aiotcloud/aicam/camera/__init__.py
aiotcloud/aicam/camera/camera.py
aiotcloud/aicam/camera/esp_server.py
aiotcloud/aicam/data/calib.io_checker_A4_8x11_20.pdf
aiotcloud/aicam/file/__init__.py
aiotcloud/aicam/file/read.py
aiotcloud/aicam/file/save.py
aiotcloud/aicam/plugins/__init__.py
aiotcloud/aicam/plugins/public_ros.py
aiotcloud/aivoice/__init__.py
aiotcloud/aivoice/aispeaker.py
aiotcloud/aivoice/playsound.py
aiotcloud/aivoice/.audio/auido.mp3
aiotcloud/fonts/ASC16_8
aiotcloud/fonts/ASC32_16
aiotcloud/fonts/HZK12
aiotcloud/fonts/HZK16
aiotcloud/rshell/__init__.py
aiotcloud/rshell/__main__.py
aiotcloud/rshell/command_line.py
aiotcloud/rshell/getch.py
aiotcloud/rshell/pyboard.py
aiotcloud/rshell/version.py
aiotcloud-2.4.5.dist-info/METADATA
aiotcloud-2.4.5.dist-info/WHEEL
aiotcloud-2.4.5.dist-info/top_level.txt
aiotcloud-2.4.5.dist-info/RECORD
