Metadata-Version: 2.1
Name: aiotcloud
Version: 2.4.5
Summary: Ver2.4.5 修复aiotcloud客户端send_map
Home-page: https://github.com/aiotcloud-tech/python-aiot-sdk
Author: sangxin
Author-email: 2876424407@qq.com
Maintainer: sangxin
Maintainer-email: 2876424407@qq.com
License: UNKNOWN
Platform: UNKNOWN
Requires-Dist: paho-mqtt
Requires-Dist: pyreadline
Requires-Dist: pyudev (>=0.16)
Requires-Dist: pyserial
Requires-Dist: pyyaml
Requires-Dist: six
Requires-Dist: playsound
Requires-Dist: baidu-aip
Requires-Dist: opencv-python
Requires-Dist: opencv-contrib-python
